<?xml version="1.0"?>
<dc-workflow workflow_id="proposal_workflow" title="Proposal Workflow" description=" - Always editable by Administrator.  States: private- proposer can edit and share, submitter can submit; submitted-owner can view but not change, manager can assign reviewers; under_review: reviewer can read and add review form; Approved/Alternate/Denied-reviewers and owner can view but not change, manager can change." state_variable="review_state" initial_state="private" manager_bypass="True">
 <permission>Access contents information</permission>
 <permission>Change portal events</permission>
 <permission>Modify portal content</permission>
 <permission>View</permission>
 <permission>Add portal content</permission>
 <permission>Sharing page: Delegate roles</permission>
 <permission>Delete objects</permission>
 <permission>Add Folders</permission>
 <permission>Add Documents, Images, and Files</permission>
 <permission>ATContentTypes: Add Link</permission>
 <permission>ATContentTypes: Add Document</permission>
 <permission>ATContentTypes: Add File</permission>
 <permission>ATContentTypes: Add Image</permission>
 <permission>ATContentTypes: Add Folder</permission>
 <permission>ATContentTypes: Upload via url</permission>
 <permission>Sharing page: Delegate Editor role</permission>
 <permission>Sharing page: Delegate Contributor role</permission>
 <permission>Sharing page: Delegate Reader role</permission>
 <permission>Sharing page: Delegate Reviewer role</permission>
 <permission>Add portal folders</permission>
 <permission>Review portal content</permission>
 <state state_id="advisor_review" title="Advisor Review">
  <description>In this state the owner (creator/original proposer) and anybody with edit permission can edit.  Anybody in a group that has the "Submitter" role can submit the proposal.</description>
  <exit-transition transition_id="send_back"/>
  <exit-transition transition_id="submit"/>
  <permission-map name="ATContentTypes: Add Document" acquired="True">
  </permission-map>
  <permission-map name="ATContentTypes: Add File" acquired="True">
  </permission-map>
  <permission-map name="ATContentTypes: Add Folder" acquired="True">
  </permission-map>
  <permission-map name="ATContentTypes: Add Image" acquired="True">
  </permission-map>
  <permission-map name="ATContentTypes: Add Link" acquired="True">
  </permission-map>
  <permission-map name="ATContentTypes: Upload via url" acquired="True">
  </permission-map>
  <permission-map name="Access contents information" acquired="False">
   <permission-role>Editor</permission-role>
   <permission-role>Manager</permission-role>
   <permission-role>Owner</permission-role>
   <permission-role>Site Administrator</permission-role>
  </permission-map>
  <permission-map name="Add Documents, Images, and Files" acquired="True">
  </permission-map>
  <permission-map name="Add Folders" acquired="True">
  </permission-map>
  <permission-map name="Add portal content" acquired="False">
   <permission-role>Editor</permission-role>
   <permission-role>Manager</permission-role>
   <permission-role>Owner</permission-role>
   <permission-role>Site Administrator</permission-role>
  </permission-map>
  <permission-map name="Change portal events" acquired="True">
   <permission-role>Manager</permission-role>
   <permission-role>Site Administrator</permission-role>
  </permission-map>
  <permission-map name="Delete objects" acquired="False">
   <permission-role>Editor</permission-role>
   <permission-role>Manager</permission-role>
   <permission-role>Owner</permission-role>
   <permission-role>Site Administrator</permission-role>
  </permission-map>
  <permission-map name="Modify portal content" acquired="False">
   <permission-role>Editor</permission-role>
   <permission-role>Manager</permission-role>
   <permission-role>Owner</permission-role>
   <permission-role>Site Administrator</permission-role>
  </permission-map>
  <permission-map name="Sharing page: Delegate Contributor role" acquired="False">
   <permission-role>Manager</permission-role>
   <permission-role>Site Administrator</permission-role>
  </permission-map>
  <permission-map name="Sharing page: Delegate Editor role" acquired="False">
   <permission-role>Editor</permission-role>
   <permission-role>Manager</permission-role>
   <permission-role>Owner</permission-role>
   <permission-role>Site Administrator</permission-role>
  </permission-map>
  <permission-map name="Sharing page: Delegate Reader role" acquired="False">
   <permission-role>Manager</permission-role>
   <permission-role>Site Administrator</permission-role>
  </permission-map>
  <permission-map name="Sharing page: Delegate Reviewer role" acquired="False">
   <permission-role>Manager</permission-role>
   <permission-role>Site Administrator</permission-role>
  </permission-map>
  <permission-map name="Sharing page: Delegate roles" acquired="False">
   <permission-role>Editor</permission-role>
   <permission-role>Manager</permission-role>
   <permission-role>Owner</permission-role>
   <permission-role>Site Administrator</permission-role>
  </permission-map>
  <permission-map name="View" acquired="False">
   <permission-role>Editor</permission-role>
   <permission-role>Manager</permission-role>
   <permission-role>Owner</permission-role>
   <permission-role>Site Administrator</permission-role>
  </permission-map>
 </state>
 <state state_id="alternate" title="Alternate">
  <description>Alternate usually means approved pending availability of funding.</description>
  <exit-transition transition_id="to_alternate_invisible"/>
  <permission-map name="ATContentTypes: Add Document" acquired="False">
   <permission-role>Manager</permission-role>
   <permission-role>Site Administrator</permission-role>
  </permission-map>
  <permission-map name="ATContentTypes: Add File" acquired="False">
   <permission-role>Manager</permission-role>
   <permission-role>Site Administrator</permission-role>
  </permission-map>
  <permission-map name="ATContentTypes: Add Folder" acquired="False">
   <permission-role>Manager</permission-role>
   <permission-role>Site Administrator</permission-role>
  </permission-map>
  <permission-map name="ATContentTypes: Add Image" acquired="False">
   <permission-role>Manager</permission-role>
   <permission-role>Site Administrator</permission-role>
  </permission-map>
  <permission-map name="ATContentTypes: Add Link" acquired="False">
   <permission-role>Manager</permission-role>
   <permission-role>Site Administrator</permission-role>
  </permission-map>
  <permission-map name="ATContentTypes: Upload via url" acquired="False">
   <permission-role>Manager</permission-role>
   <permission-role>Site Administrator</permission-role>
  </permission-map>
  <permission-map name="Access contents information" acquired="False">
   <permission-role>Editor</permission-role>
   <permission-role>Manager</permission-role>
   <permission-role>Owner</permission-role>
   <permission-role>Reviewer</permission-role>
   <permission-role>Site Administrator</permission-role>
   <permission-role>panelist</permission-role>
  </permission-map>
  <permission-map name="Add Documents, Images, and Files" acquired="False">
   <permission-role>Manager</permission-role>
   <permission-role>Site Administrator</permission-role>
  </permission-map>
  <permission-map name="Add Folders" acquired="False">
   <permission-role>Manager</permission-role>
   <permission-role>Site Administrator</permission-role>
  </permission-map>
  <permission-map name="Add portal content" acquired="False">
   <permission-role>Manager</permission-role>
   <permission-role>Site Administrator</permission-role>
  </permission-map>
  <permission-map name="Add portal folders" acquired="False">
   <permission-role>Manager</permission-role>
   <permission-role>Site Administrator</permission-role>
  </permission-map>
  <permission-map name="Change portal events" acquired="False">
   <permission-role>Manager</permission-role>
   <permission-role>Site Administrator</permission-role>
  </permission-map>
  <permission-map name="Delete objects" acquired="False">
   <permission-role>Manager</permission-role>
   <permission-role>Site Administrator</permission-role>
  </permission-map>
  <permission-map name="Modify portal content" acquired="False">
   <permission-role>Manager</permission-role>
   <permission-role>Site Administrator</permission-role>
  </permission-map>
  <permission-map name="Review portal content" acquired="False">
   <permission-role>Manager</permission-role>
   <permission-role>Site Administrator</permission-role>
  </permission-map>
  <permission-map name="Sharing page: Delegate Contributor role" acquired="False">
   <permission-role>Manager</permission-role>
   <permission-role>Site Administrator</permission-role>
  </permission-map>
  <permission-map name="Sharing page: Delegate Editor role" acquired="False">
   <permission-role>Manager</permission-role>
   <permission-role>Site Administrator</permission-role>
  </permission-map>
  <permission-map name="Sharing page: Delegate Reader role" acquired="False">
   <permission-role>Editor</permission-role>
   <permission-role>Manager</permission-role>
   <permission-role>Owner</permission-role>
   <permission-role>Site Administrator</permission-role>
  </permission-map>
  <permission-map name="Sharing page: Delegate Reviewer role" acquired="False">
  </permission-map>
  <permission-map name="Sharing page: Delegate roles" acquired="False">
   <permission-role>Editor</permission-role>
   <permission-role>Manager</permission-role>
   <permission-role>Owner</permission-role>
   <permission-role>Reviewer</permission-role>
   <permission-role>Site Administrator</permission-role>
   <permission-role>panelist</permission-role>
  </permission-map>
  <permission-map name="View" acquired="False">
   <permission-role>Editor</permission-role>
   <permission-role>Manager</permission-role>
   <permission-role>Owner</permission-role>
   <permission-role>Reviewer</permission-role>
   <permission-role>Site Administrator</permission-role>
   <permission-role>panelist</permission-role>
  </permission-map>
 </state>
 <state state_id="alternate_invisible" title="">
  <exit-transition transition_id="to_alternate"/>
  <exit-transition transition_id="to_approved_invisible"/>
  <exit-transition transition_id="to_denied_invisible"/>
  <exit-transition transition_id="to_panel_review"/>
  <permission-map name="ATContentTypes: Add Document" acquired="False">
   <permission-role>Manager</permission-role>
   <permission-role>Site Administrator</permission-role>
  </permission-map>
  <permission-map name="ATContentTypes: Add File" acquired="False">
   <permission-role>Manager</permission-role>
   <permission-role>Site Administrator</permission-role>
  </permission-map>
  <permission-map name="ATContentTypes: Add Folder" acquired="False">
   <permission-role>Manager</permission-role>
   <permission-role>Site Administrator</permission-role>
  </permission-map>
  <permission-map name="ATContentTypes: Add Image" acquired="False">
   <permission-role>Manager</permission-role>
   <permission-role>Site Administrator</permission-role>
  </permission-map>
  <permission-map name="ATContentTypes: Add Link" acquired="False">
   <permission-role>Manager</permission-role>
   <permission-role>Site Administrator</permission-role>
  </permission-map>
  <permission-map name="ATContentTypes: Upload via url" acquired="False">
   <permission-role>Manager</permission-role>
   <permission-role>Site Administrator</permission-role>
  </permission-map>
  <permission-map name="Access contents information" acquired="False">
   <permission-role>Manager</permission-role>
   <permission-role>Site Administrator</permission-role>
   <permission-role>panelist</permission-role>
  </permission-map>
  <permission-map name="Add Documents, Images, and Files" acquired="False">
   <permission-role>Manager</permission-role>
   <permission-role>Site Administrator</permission-role>
  </permission-map>
  <permission-map name="Add Folders" acquired="False">
   <permission-role>Manager</permission-role>
   <permission-role>Site Administrator</permission-role>
  </permission-map>
  <permission-map name="Add portal content" acquired="False">
   <permission-role>Manager</permission-role>
   <permission-role>Site Administrator</permission-role>
  </permission-map>
  <permission-map name="Add portal folders" acquired="False">
   <permission-role>Manager</permission-role>
   <permission-role>Site Administrator</permission-role>
  </permission-map>
  <permission-map name="Change portal events" acquired="False">
   <permission-role>Manager</permission-role>
   <permission-role>Site Administrator</permission-role>
  </permission-map>
  <permission-map name="Delete objects" acquired="False">
   <permission-role>Manager</permission-role>
   <permission-role>Site Administrator</permission-role>
  </permission-map>
  <permission-map name="Modify portal content" acquired="False">
   <permission-role>Manager</permission-role>
   <permission-role>Site Administrator</permission-role>
  </permission-map>
  <permission-map name="Review portal content" acquired="False">
   <permission-role>Manager</permission-role>
   <permission-role>Site Administrator</permission-role>
  </permission-map>
  <permission-map name="Sharing page: Delegate Contributor role" acquired="False">
   <permission-role>Manager</permission-role>
   <permission-role>Site Administrator</permission-role>
  </permission-map>
  <permission-map name="Sharing page: Delegate Editor role" acquired="False">
   <permission-role>Manager</permission-role>
   <permission-role>Site Administrator</permission-role>
  </permission-map>
  <permission-map name="Sharing page: Delegate Reader role" acquired="False">
   <permission-role>Manager</permission-role>
   <permission-role>Site Administrator</permission-role>
  </permission-map>
  <permission-map name="Sharing page: Delegate Reviewer role" acquired="False">
  </permission-map>
  <permission-map name="Sharing page: Delegate roles" acquired="False">
   <permission-role>Manager</permission-role>
   <permission-role>Site Administrator</permission-role>
   <permission-role>panelist</permission-role>
  </permission-map>
  <permission-map name="View" acquired="False">
   <permission-role>Manager</permission-role>
   <permission-role>Site Administrator</permission-role>
   <permission-role>panelist</permission-role>
  </permission-map>
 </state>
 <state state_id="approved" title="Approved">
  <exit-transition transition_id="to_approved_invisible"/>
  <permission-map name="ATContentTypes: Add Document" acquired="False">
   <permission-role>Manager</permission-role>
   <permission-role>Site Administrator</permission-role>
  </permission-map>
  <permission-map name="ATContentTypes: Add File" acquired="False">
   <permission-role>Manager</permission-role>
   <permission-role>Site Administrator</permission-role>
  </permission-map>
  <permission-map name="ATContentTypes: Add Folder" acquired="False">
   <permission-role>Manager</permission-role>
   <permission-role>Site Administrator</permission-role>
  </permission-map>
  <permission-map name="ATContentTypes: Add Image" acquired="False">
   <permission-role>Manager</permission-role>
   <permission-role>Site Administrator</permission-role>
  </permission-map>
  <permission-map name="ATContentTypes: Add Link" acquired="False">
   <permission-role>Manager</permission-role>
   <permission-role>Site Administrator</permission-role>
  </permission-map>
  <permission-map name="ATContentTypes: Upload via url" acquired="False">
   <permission-role>Manager</permission-role>
   <permission-role>Site Administrator</permission-role>
  </permission-map>
  <permission-map name="Access contents information" acquired="False">
   <permission-role>Editor</permission-role>
   <permission-role>Manager</permission-role>
   <permission-role>Owner</permission-role>
   <permission-role>Reviewer</permission-role>
   <permission-role>Site Administrator</permission-role>
   <permission-role>panelist</permission-role>
  </permission-map>
  <permission-map name="Add Documents, Images, and Files" acquired="False">
   <permission-role>Manager</permission-role>
   <permission-role>Site Administrator</permission-role>
  </permission-map>
  <permission-map name="Add Folders" acquired="False">
   <permission-role>Manager</permission-role>
   <permission-role>Site Administrator</permission-role>
  </permission-map>
  <permission-map name="Add portal content" acquired="False">
   <permission-role>Manager</permission-role>
   <permission-role>Site Administrator</permission-role>
  </permission-map>
  <permission-map name="Add portal folders" acquired="False">
   <permission-role>Manager</permission-role>
   <permission-role>Site Administrator</permission-role>
  </permission-map>
  <permission-map name="Change portal events" acquired="False">
   <permission-role>Manager</permission-role>
   <permission-role>Site Administrator</permission-role>
  </permission-map>
  <permission-map name="Delete objects" acquired="False">
   <permission-role>Manager</permission-role>
   <permission-role>Site Administrator</permission-role>
  </permission-map>
  <permission-map name="Modify portal content" acquired="False">
   <permission-role>Manager</permission-role>
   <permission-role>Site Administrator</permission-role>
  </permission-map>
  <permission-map name="Review portal content" acquired="False">
   <permission-role>Manager</permission-role>
   <permission-role>Site Administrator</permission-role>
  </permission-map>
  <permission-map name="Sharing page: Delegate Contributor role" acquired="False">
   <permission-role>Manager</permission-role>
   <permission-role>Site Administrator</permission-role>
  </permission-map>
  <permission-map name="Sharing page: Delegate Editor role" acquired="False">
   <permission-role>Manager</permission-role>
   <permission-role>Site Administrator</permission-role>
  </permission-map>
  <permission-map name="Sharing page: Delegate Reader role" acquired="False">
   <permission-role>Manager</permission-role>
   <permission-role>Site Administrator</permission-role>
  </permission-map>
  <permission-map name="Sharing page: Delegate Reviewer role" acquired="False">
  </permission-map>
  <permission-map name="Sharing page: Delegate roles" acquired="False">
   <permission-role>Editor</permission-role>
   <permission-role>Manager</permission-role>
   <permission-role>Owner</permission-role>
   <permission-role>Reviewer</permission-role>
   <permission-role>Site Administrator</permission-role>
   <permission-role>panelist</permission-role>
  </permission-map>
  <permission-map name="View" acquired="False">
   <permission-role>Editor</permission-role>
   <permission-role>Manager</permission-role>
   <permission-role>Owner</permission-role>
   <permission-role>Reviewer</permission-role>
   <permission-role>Site Administrator</permission-role>
   <permission-role>panelist</permission-role>
  </permission-map>
 </state>
 <state state_id="approved_invisible" title="">
  <exit-transition transition_id="to_alternate_invisible"/>
  <exit-transition transition_id="to_approved"/>
  <exit-transition transition_id="to_denied_invisible"/>
  <exit-transition transition_id="to_panel_review"/>
  <permission-map name="ATContentTypes: Add Document" acquired="False">
   <permission-role>Manager</permission-role>
   <permission-role>Site Administrator</permission-role>
  </permission-map>
  <permission-map name="ATContentTypes: Add File" acquired="False">
   <permission-role>Manager</permission-role>
   <permission-role>Site Administrator</permission-role>
  </permission-map>
  <permission-map name="ATContentTypes: Add Folder" acquired="False">
   <permission-role>Manager</permission-role>
   <permission-role>Site Administrator</permission-role>
  </permission-map>
  <permission-map name="ATContentTypes: Add Image" acquired="False">
   <permission-role>Manager</permission-role>
   <permission-role>Site Administrator</permission-role>
  </permission-map>
  <permission-map name="ATContentTypes: Add Link" acquired="False">
   <permission-role>Manager</permission-role>
   <permission-role>Site Administrator</permission-role>
  </permission-map>
  <permission-map name="ATContentTypes: Upload via url" acquired="False">
   <permission-role>Manager</permission-role>
   <permission-role>Site Administrator</permission-role>
  </permission-map>
  <permission-map name="Access contents information" acquired="False">
   <permission-role>Manager</permission-role>
   <permission-role>Site Administrator</permission-role>
   <permission-role>panelist</permission-role>
  </permission-map>
  <permission-map name="Add Documents, Images, and Files" acquired="False">
   <permission-role>Manager</permission-role>
   <permission-role>Site Administrator</permission-role>
  </permission-map>
  <permission-map name="Add Folders" acquired="False">
   <permission-role>Manager</permission-role>
   <permission-role>Site Administrator</permission-role>
  </permission-map>
  <permission-map name="Add portal content" acquired="False">
   <permission-role>Manager</permission-role>
   <permission-role>Site Administrator</permission-role>
  </permission-map>
  <permission-map name="Add portal folders" acquired="False">
   <permission-role>Manager</permission-role>
   <permission-role>Site Administrator</permission-role>
  </permission-map>
  <permission-map name="Change portal events" acquired="False">
   <permission-role>Manager</permission-role>
   <permission-role>Site Administrator</permission-role>
  </permission-map>
  <permission-map name="Delete objects" acquired="False">
   <permission-role>Manager</permission-role>
   <permission-role>Site Administrator</permission-role>
  </permission-map>
  <permission-map name="Modify portal content" acquired="False">
   <permission-role>Manager</permission-role>
   <permission-role>Site Administrator</permission-role>
  </permission-map>
  <permission-map name="Review portal content" acquired="False">
   <permission-role>Manager</permission-role>
   <permission-role>Site Administrator</permission-role>
  </permission-map>
  <permission-map name="Sharing page: Delegate Contributor role" acquired="False">
   <permission-role>Manager</permission-role>
   <permission-role>Site Administrator</permission-role>
  </permission-map>
  <permission-map name="Sharing page: Delegate Editor role" acquired="False">
   <permission-role>Manager</permission-role>
   <permission-role>Site Administrator</permission-role>
  </permission-map>
  <permission-map name="Sharing page: Delegate Reader role" acquired="False">
   <permission-role>Manager</permission-role>
   <permission-role>Site Administrator</permission-role>
  </permission-map>
  <permission-map name="Sharing page: Delegate Reviewer role" acquired="False">
  </permission-map>
  <permission-map name="Sharing page: Delegate roles" acquired="False">
   <permission-role>Manager</permission-role>
   <permission-role>Site Administrator</permission-role>
   <permission-role>panelist</permission-role>
  </permission-map>
  <permission-map name="View" acquired="False">
   <permission-role>Manager</permission-role>
   <permission-role>Site Administrator</permission-role>
   <permission-role>panelist</permission-role>
  </permission-map>
 </state>
 <state state_id="denied" title="Denied">
  <exit-transition transition_id="to_denied_invisible"/>
  <permission-map name="ATContentTypes: Add Document" acquired="False">
   <permission-role>Manager</permission-role>
   <permission-role>Site Administrator</permission-role>
  </permission-map>
  <permission-map name="ATContentTypes: Add File" acquired="False">
   <permission-role>Manager</permission-role>
   <permission-role>Site Administrator</permission-role>
  </permission-map>
  <permission-map name="ATContentTypes: Add Folder" acquired="False">
   <permission-role>Manager</permission-role>
   <permission-role>Site Administrator</permission-role>
  </permission-map>
  <permission-map name="ATContentTypes: Add Image" acquired="False">
   <permission-role>Manager</permission-role>
   <permission-role>Site Administrator</permission-role>
  </permission-map>
  <permission-map name="ATContentTypes: Add Link" acquired="False">
   <permission-role>Manager</permission-role>
   <permission-role>Site Administrator</permission-role>
  </permission-map>
  <permission-map name="ATContentTypes: Upload via url" acquired="False">
   <permission-role>Manager</permission-role>
   <permission-role>Site Administrator</permission-role>
  </permission-map>
  <permission-map name="Access contents information" acquired="False">
   <permission-role>Editor</permission-role>
   <permission-role>Manager</permission-role>
   <permission-role>Owner</permission-role>
   <permission-role>Reviewer</permission-role>
   <permission-role>Site Administrator</permission-role>
   <permission-role>panelist</permission-role>
  </permission-map>
  <permission-map name="Add Documents, Images, and Files" acquired="False">
   <permission-role>Manager</permission-role>
   <permission-role>Site Administrator</permission-role>
  </permission-map>
  <permission-map name="Add Folders" acquired="False">
   <permission-role>Manager</permission-role>
   <permission-role>Site Administrator</permission-role>
  </permission-map>
  <permission-map name="Add portal content" acquired="False">
   <permission-role>Manager</permission-role>
   <permission-role>Site Administrator</permission-role>
  </permission-map>
  <permission-map name="Add portal folders" acquired="False">
   <permission-role>Manager</permission-role>
   <permission-role>Site Administrator</permission-role>
  </permission-map>
  <permission-map name="Change portal events" acquired="False">
   <permission-role>Manager</permission-role>
   <permission-role>Site Administrator</permission-role>
  </permission-map>
  <permission-map name="Delete objects" acquired="False">
   <permission-role>Manager</permission-role>
   <permission-role>Site Administrator</permission-role>
  </permission-map>
  <permission-map name="Modify portal content" acquired="False">
   <permission-role>Manager</permission-role>
   <permission-role>Site Administrator</permission-role>
  </permission-map>
  <permission-map name="Review portal content" acquired="False">
   <permission-role>Manager</permission-role>
   <permission-role>Site Administrator</permission-role>
  </permission-map>
  <permission-map name="Sharing page: Delegate Contributor role" acquired="False">
   <permission-role>Manager</permission-role>
   <permission-role>Site Administrator</permission-role>
  </permission-map>
  <permission-map name="Sharing page: Delegate Editor role" acquired="False">
   <permission-role>Manager</permission-role>
   <permission-role>Site Administrator</permission-role>
  </permission-map>
  <permission-map name="Sharing page: Delegate Reader role" acquired="False">
   <permission-role>Editor</permission-role>
   <permission-role>Manager</permission-role>
   <permission-role>Owner</permission-role>
   <permission-role>Site Administrator</permission-role>
  </permission-map>
  <permission-map name="Sharing page: Delegate Reviewer role" acquired="False">
  </permission-map>
  <permission-map name="Sharing page: Delegate roles" acquired="False">
   <permission-role>Editor</permission-role>
   <permission-role>Manager</permission-role>
   <permission-role>Owner</permission-role>
   <permission-role>Reviewer</permission-role>
   <permission-role>Site Administrator</permission-role>
   <permission-role>panelist</permission-role>
  </permission-map>
  <permission-map name="View" acquired="False">
   <permission-role>Editor</permission-role>
   <permission-role>Manager</permission-role>
   <permission-role>Owner</permission-role>
   <permission-role>Reviewer</permission-role>
   <permission-role>Site Administrator</permission-role>
   <permission-role>panelist</permission-role>
  </permission-map>
 </state>
 <state state_id="denied_invisible" title="">
  <exit-transition transition_id="to_alternate_invisible"/>
  <exit-transition transition_id="to_approved_invisible"/>
  <exit-transition transition_id="to_denied"/>
  <exit-transition transition_id="to_panel_review"/>
  <permission-map name="ATContentTypes: Add Document" acquired="False">
   <permission-role>Manager</permission-role>
   <permission-role>Site Administrator</permission-role>
  </permission-map>
  <permission-map name="ATContentTypes: Add File" acquired="False">
   <permission-role>Manager</permission-role>
   <permission-role>Site Administrator</permission-role>
  </permission-map>
  <permission-map name="ATContentTypes: Add Folder" acquired="False">
   <permission-role>Manager</permission-role>
   <permission-role>Site Administrator</permission-role>
  </permission-map>
  <permission-map name="ATContentTypes: Add Image" acquired="False">
   <permission-role>Manager</permission-role>
   <permission-role>Site Administrator</permission-role>
  </permission-map>
  <permission-map name="ATContentTypes: Add Link" acquired="False">
   <permission-role>Manager</permission-role>
   <permission-role>Site Administrator</permission-role>
  </permission-map>
  <permission-map name="ATContentTypes: Upload via url" acquired="False">
   <permission-role>Manager</permission-role>
   <permission-role>Site Administrator</permission-role>
  </permission-map>
  <permission-map name="Access contents information" acquired="False">
   <permission-role>Manager</permission-role>
   <permission-role>Site Administrator</permission-role>
   <permission-role>panelist</permission-role>
  </permission-map>
  <permission-map name="Add Documents, Images, and Files" acquired="False">
   <permission-role>Manager</permission-role>
   <permission-role>Site Administrator</permission-role>
  </permission-map>
  <permission-map name="Add Folders" acquired="False">
   <permission-role>Manager</permission-role>
   <permission-role>Site Administrator</permission-role>
  </permission-map>
  <permission-map name="Add portal content" acquired="False">
   <permission-role>Manager</permission-role>
   <permission-role>Site Administrator</permission-role>
  </permission-map>
  <permission-map name="Add portal folders" acquired="False">
   <permission-role>Manager</permission-role>
   <permission-role>Site Administrator</permission-role>
  </permission-map>
  <permission-map name="Change portal events" acquired="False">
   <permission-role>Manager</permission-role>
   <permission-role>Site Administrator</permission-role>
  </permission-map>
  <permission-map name="Delete objects" acquired="False">
   <permission-role>Manager</permission-role>
   <permission-role>Site Administrator</permission-role>
  </permission-map>
  <permission-map name="Modify portal content" acquired="False">
   <permission-role>Manager</permission-role>
   <permission-role>Site Administrator</permission-role>
  </permission-map>
  <permission-map name="Review portal content" acquired="False">
   <permission-role>Manager</permission-role>
   <permission-role>Site Administrator</permission-role>
  </permission-map>
  <permission-map name="Sharing page: Delegate Contributor role" acquired="False">
   <permission-role>Manager</permission-role>
   <permission-role>Site Administrator</permission-role>
  </permission-map>
  <permission-map name="Sharing page: Delegate Editor role" acquired="False">
   <permission-role>Manager</permission-role>
   <permission-role>Site Administrator</permission-role>
  </permission-map>
  <permission-map name="Sharing page: Delegate Reader role" acquired="False">
   <permission-role>Manager</permission-role>
   <permission-role>Site Administrator</permission-role>
  </permission-map>
  <permission-map name="Sharing page: Delegate Reviewer role" acquired="False">
  </permission-map>
  <permission-map name="Sharing page: Delegate roles" acquired="False">
   <permission-role>Manager</permission-role>
   <permission-role>Site Administrator</permission-role>
   <permission-role>panelist</permission-role>
  </permission-map>
  <permission-map name="View" acquired="False">
   <permission-role>Manager</permission-role>
   <permission-role>Site Administrator</permission-role>
   <permission-role>panelist</permission-role>
  </permission-map>
 </state>
 <state state_id="panel_review" title="Panel Review">
  <description>Only panelists and administrators can access reviews in this state.</description>
  <exit-transition transition_id="to_alternate_invisible"/>
  <exit-transition transition_id="to_approved_invisible"/>
  <exit-transition transition_id="to_denied_invisible"/>
  <exit-transition transition_id="to_under_review"/>
  <permission-map name="ATContentTypes: Add Document" acquired="False">
   <permission-role>Manager</permission-role>
   <permission-role>Site Administrator</permission-role>
  </permission-map>
  <permission-map name="ATContentTypes: Add File" acquired="False">
   <permission-role>Manager</permission-role>
   <permission-role>Site Administrator</permission-role>
  </permission-map>
  <permission-map name="ATContentTypes: Add Folder" acquired="False">
   <permission-role>Manager</permission-role>
   <permission-role>Site Administrator</permission-role>
  </permission-map>
  <permission-map name="ATContentTypes: Add Image" acquired="False">
   <permission-role>Manager</permission-role>
   <permission-role>Site Administrator</permission-role>
  </permission-map>
  <permission-map name="ATContentTypes: Add Link" acquired="False">
   <permission-role>Manager</permission-role>
   <permission-role>Site Administrator</permission-role>
  </permission-map>
  <permission-map name="ATContentTypes: Upload via url" acquired="False">
   <permission-role>Manager</permission-role>
   <permission-role>Site Administrator</permission-role>
  </permission-map>
  <permission-map name="Access contents information" acquired="False">
   <permission-role>Manager</permission-role>
   <permission-role>Site Administrator</permission-role>
   <permission-role>panelist</permission-role>
  </permission-map>
  <permission-map name="Add Documents, Images, and Files" acquired="False">
   <permission-role>Manager</permission-role>
   <permission-role>Site Administrator</permission-role>
  </permission-map>
  <permission-map name="Add Folders" acquired="False">
   <permission-role>Manager</permission-role>
   <permission-role>Site Administrator</permission-role>
  </permission-map>
  <permission-map name="Add portal content" acquired="False">
   <permission-role>Manager</permission-role>
   <permission-role>Site Administrator</permission-role>
  </permission-map>
  <permission-map name="Add portal folders" acquired="False">
   <permission-role>Manager</permission-role>
   <permission-role>Site Administrator</permission-role>
  </permission-map>
  <permission-map name="Change portal events" acquired="False">
   <permission-role>Manager</permission-role>
   <permission-role>Site Administrator</permission-role>
  </permission-map>
  <permission-map name="Delete objects" acquired="False">
   <permission-role>Manager</permission-role>
   <permission-role>Site Administrator</permission-role>
  </permission-map>
  <permission-map name="Modify portal content" acquired="False">
   <permission-role>Manager</permission-role>
   <permission-role>Site Administrator</permission-role>
  </permission-map>
  <permission-map name="Review portal content" acquired="False">
   <permission-role>Manager</permission-role>
   <permission-role>Site Administrator</permission-role>
  </permission-map>
  <permission-map name="Sharing page: Delegate Contributor role" acquired="False">
   <permission-role>Manager</permission-role>
   <permission-role>Site Administrator</permission-role>
  </permission-map>
  <permission-map name="Sharing page: Delegate Editor role" acquired="False">
   <permission-role>Manager</permission-role>
   <permission-role>Site Administrator</permission-role>
  </permission-map>
  <permission-map name="Sharing page: Delegate Reader role" acquired="False">
   <permission-role>Manager</permission-role>
   <permission-role>Site Administrator</permission-role>
  </permission-map>
  <permission-map name="Sharing page: Delegate Reviewer role" acquired="False">
  </permission-map>
  <permission-map name="Sharing page: Delegate roles" acquired="False">
   <permission-role>Manager</permission-role>
   <permission-role>Site Administrator</permission-role>
   <permission-role>panelist</permission-role>
  </permission-map>
  <permission-map name="View" acquired="False">
   <permission-role>Manager</permission-role>
   <permission-role>Site Administrator</permission-role>
   <permission-role>panelist</permission-role>
  </permission-map>
 </state>
 <state state_id="private" title="Private">
  <description>Can only be seen and edited by the owner.</description>
  <exit-transition transition_id="submit"/>
  <exit-transition transition_id="to_advisor_review"/>
  <permission-map name="ATContentTypes: Add Document" acquired="True">
  </permission-map>
  <permission-map name="ATContentTypes: Add File" acquired="True">
  </permission-map>
  <permission-map name="ATContentTypes: Add Folder" acquired="True">
  </permission-map>
  <permission-map name="ATContentTypes: Add Image" acquired="True">
  </permission-map>
  <permission-map name="ATContentTypes: Add Link" acquired="True">
  </permission-map>
  <permission-map name="ATContentTypes: Upload via url" acquired="True">
  </permission-map>
  <permission-map name="Access contents information" acquired="False">
   <permission-role>Editor</permission-role>
   <permission-role>Manager</permission-role>
   <permission-role>Owner</permission-role>
   <permission-role>Site Administrator</permission-role>
  </permission-map>
  <permission-map name="Add Documents, Images, and Files" acquired="True">
  </permission-map>
  <permission-map name="Add Folders" acquired="True">
  </permission-map>
  <permission-map name="Add portal content" acquired="False">
   <permission-role>Editor</permission-role>
   <permission-role>Manager</permission-role>
   <permission-role>Owner</permission-role>
   <permission-role>Site Administrator</permission-role>
  </permission-map>
  <permission-map name="Add portal folders" acquired="True">
  </permission-map>
  <permission-map name="Change portal events" acquired="True">
   <permission-role>Manager</permission-role>
   <permission-role>Owner</permission-role>
   <permission-role>Site Administrator</permission-role>
  </permission-map>
  <permission-map name="Delete objects" acquired="False">
   <permission-role>Editor</permission-role>
   <permission-role>Manager</permission-role>
   <permission-role>Owner</permission-role>
   <permission-role>Site Administrator</permission-role>
  </permission-map>
  <permission-map name="Modify portal content" acquired="False">
   <permission-role>Editor</permission-role>
   <permission-role>Manager</permission-role>
   <permission-role>Owner</permission-role>
   <permission-role>Site Administrator</permission-role>
  </permission-map>
  <permission-map name="Sharing page: Delegate Contributor role" acquired="False">
   <permission-role>Manager</permission-role>
   <permission-role>Site Administrator</permission-role>
  </permission-map>
  <permission-map name="Sharing page: Delegate Editor role" acquired="False">
   <permission-role>Editor</permission-role>
   <permission-role>Manager</permission-role>
   <permission-role>Owner</permission-role>
   <permission-role>Site Administrator</permission-role>
  </permission-map>
  <permission-map name="Sharing page: Delegate Reader role" acquired="False">
   <permission-role>Manager</permission-role>
   <permission-role>Site Administrator</permission-role>
  </permission-map>
  <permission-map name="Sharing page: Delegate Reviewer role" acquired="False">
   <permission-role>Manager</permission-role>
   <permission-role>Site Administrator</permission-role>
  </permission-map>
  <permission-map name="Sharing page: Delegate roles" acquired="False">
   <permission-role>Editor</permission-role>
   <permission-role>Manager</permission-role>
   <permission-role>Owner</permission-role>
   <permission-role>Site Administrator</permission-role>
  </permission-map>
  <permission-map name="View" acquired="False">
   <permission-role>Editor</permission-role>
   <permission-role>Manager</permission-role>
   <permission-role>Owner</permission-role>
   <permission-role>Site Administrator</permission-role>
  </permission-map>
 </state>
 <state state_id="submitted" title="Submitted">
  <description>Item is ready for grading and review.</description>
  <exit-transition transition_id="retract"/>
  <exit-transition transition_id="send_back"/>
  <exit-transition transition_id="to_under_review"/>
  <permission-map name="ATContentTypes: Add Document" acquired="False">
   <permission-role>Manager</permission-role>
   <permission-role>Site Administrator</permission-role>
  </permission-map>
  <permission-map name="ATContentTypes: Add File" acquired="False">
   <permission-role>Manager</permission-role>
   <permission-role>Site Administrator</permission-role>
  </permission-map>
  <permission-map name="ATContentTypes: Add Folder" acquired="False">
   <permission-role>Manager</permission-role>
   <permission-role>Site Administrator</permission-role>
  </permission-map>
  <permission-map name="ATContentTypes: Add Image" acquired="False">
   <permission-role>Manager</permission-role>
   <permission-role>Site Administrator</permission-role>
  </permission-map>
  <permission-map name="ATContentTypes: Add Link" acquired="False">
   <permission-role>Manager</permission-role>
   <permission-role>Site Administrator</permission-role>
  </permission-map>
  <permission-map name="ATContentTypes: Upload via url" acquired="False">
   <permission-role>Manager</permission-role>
   <permission-role>Site Administrator</permission-role>
  </permission-map>
  <permission-map name="Access contents information" acquired="False">
   <permission-role>Editor</permission-role>
   <permission-role>Manager</permission-role>
   <permission-role>Owner</permission-role>
   <permission-role>Site Administrator</permission-role>
  </permission-map>
  <permission-map name="Add Documents, Images, and Files" acquired="False">
   <permission-role>Manager</permission-role>
   <permission-role>Site Administrator</permission-role>
  </permission-map>
  <permission-map name="Add Folders" acquired="False">
   <permission-role>Manager</permission-role>
   <permission-role>Site Administrator</permission-role>
  </permission-map>
  <permission-map name="Add portal content" acquired="False">
   <permission-role>Manager</permission-role>
   <permission-role>Site Administrator</permission-role>
  </permission-map>
  <permission-map name="Add portal folders" acquired="False">
   <permission-role>Manager</permission-role>
   <permission-role>Site Administrator</permission-role>
  </permission-map>
  <permission-map name="Change portal events" acquired="False">
   <permission-role>Manager</permission-role>
   <permission-role>Site Administrator</permission-role>
  </permission-map>
  <permission-map name="Delete objects" acquired="False">
   <permission-role>Manager</permission-role>
   <permission-role>Site Administrator</permission-role>
  </permission-map>
  <permission-map name="Modify portal content" acquired="False">
   <permission-role>Manager</permission-role>
   <permission-role>Site Administrator</permission-role>
  </permission-map>
  <permission-map name="Review portal content" acquired="False">
   <permission-role>Manager</permission-role>
   <permission-role>Site Administrator</permission-role>
  </permission-map>
  <permission-map name="Sharing page: Delegate Contributor role" acquired="False">
   <permission-role>Manager</permission-role>
   <permission-role>Site Administrator</permission-role>
  </permission-map>
  <permission-map name="Sharing page: Delegate Editor role" acquired="False">
   <permission-role>Manager</permission-role>
   <permission-role>Site Administrator</permission-role>
  </permission-map>
  <permission-map name="Sharing page: Delegate Reader role" acquired="False">
   <permission-role>Manager</permission-role>
   <permission-role>Site Administrator</permission-role>
  </permission-map>
  <permission-map name="Sharing page: Delegate Reviewer role" acquired="False">
   <permission-role>Manager</permission-role>
   <permission-role>Site Administrator</permission-role>
  </permission-map>
  <permission-map name="Sharing page: Delegate roles" acquired="False">
   <permission-role>Editor</permission-role>
   <permission-role>Manager</permission-role>
   <permission-role>Owner</permission-role>
   <permission-role>Site Administrator</permission-role>
  </permission-map>
  <permission-map name="View" acquired="False">
   <permission-role>Editor</permission-role>
   <permission-role>Manager</permission-role>
   <permission-role>Owner</permission-role>
   <permission-role>Site Administrator</permission-role>
  </permission-map>
 </state>
 <state state_id="under_review" title="Under Review">
  <description>In this state reviewers and owners can see the proposals</description>
  <exit-transition transition_id="submit"/>
  <exit-transition transition_id="to_panel_review"/>
  <permission-map name="ATContentTypes: Add Document" acquired="False">
   <permission-role>Manager</permission-role>
   <permission-role>Site Administrator</permission-role>
  </permission-map>
  <permission-map name="ATContentTypes: Add File" acquired="False">
   <permission-role>Manager</permission-role>
   <permission-role>Site Administrator</permission-role>
  </permission-map>
  <permission-map name="ATContentTypes: Add Folder" acquired="False">
   <permission-role>Manager</permission-role>
   <permission-role>Site Administrator</permission-role>
  </permission-map>
  <permission-map name="ATContentTypes: Add Image" acquired="False">
   <permission-role>Manager</permission-role>
   <permission-role>Site Administrator</permission-role>
  </permission-map>
  <permission-map name="ATContentTypes: Add Link" acquired="False">
   <permission-role>Manager</permission-role>
   <permission-role>Site Administrator</permission-role>
  </permission-map>
  <permission-map name="ATContentTypes: Upload via url" acquired="False">
   <permission-role>Manager</permission-role>
   <permission-role>Site Administrator</permission-role>
  </permission-map>
  <permission-map name="Access contents information" acquired="False">
   <permission-role>Manager</permission-role>
   <permission-role>Reviewer</permission-role>
   <permission-role>Site Administrator</permission-role>
  </permission-map>
  <permission-map name="Add Documents, Images, and Files" acquired="False">
   <permission-role>Manager</permission-role>
   <permission-role>Site Administrator</permission-role>
  </permission-map>
  <permission-map name="Add Folders" acquired="False">
   <permission-role>Manager</permission-role>
   <permission-role>Site Administrator</permission-role>
  </permission-map>
  <permission-map name="Add portal content" acquired="False">
   <permission-role>Manager</permission-role>
   <permission-role>Reviewer</permission-role>
   <permission-role>Site Administrator</permission-role>
  </permission-map>
  <permission-map name="Add portal folders" acquired="False">
   <permission-role>Manager</permission-role>
   <permission-role>Site Administrator</permission-role>
  </permission-map>
  <permission-map name="Change portal events" acquired="False">
   <permission-role>Manager</permission-role>
   <permission-role>Site Administrator</permission-role>
  </permission-map>
  <permission-map name="Delete objects" acquired="False">
   <permission-role>Manager</permission-role>
   <permission-role>Site Administrator</permission-role>
  </permission-map>
  <permission-map name="Modify portal content" acquired="False">
   <permission-role>Manager</permission-role>
   <permission-role>Site Administrator</permission-role>
  </permission-map>
  <permission-map name="Review portal content" acquired="False">
   <permission-role>Manager</permission-role>
   <permission-role>Reviewer</permission-role>
   <permission-role>Site Administrator</permission-role>
  </permission-map>
  <permission-map name="Sharing page: Delegate Contributor role" acquired="False">
   <permission-role>Manager</permission-role>
   <permission-role>Site Administrator</permission-role>
  </permission-map>
  <permission-map name="Sharing page: Delegate Editor role" acquired="False">
   <permission-role>Manager</permission-role>
   <permission-role>Site Administrator</permission-role>
  </permission-map>
  <permission-map name="Sharing page: Delegate Reader role" acquired="False">
   <permission-role>Manager</permission-role>
   <permission-role>Site Administrator</permission-role>
  </permission-map>
  <permission-map name="Sharing page: Delegate Reviewer role" acquired="False">
   <permission-role>Manager</permission-role>
   <permission-role>Site Administrator</permission-role>
  </permission-map>
  <permission-map name="Sharing page: Delegate roles" acquired="False">
   <permission-role>Manager</permission-role>
   <permission-role>Site Administrator</permission-role>
  </permission-map>
  <permission-map name="View" acquired="False">
   <permission-role>Manager</permission-role>
   <permission-role>Reviewer</permission-role>
   <permission-role>Site Administrator</permission-role>
  </permission-map>
 </state>
 <transition transition_id="retract" title="Retract Submission" new_state="private" trigger="USER" before_script="" after_script="">
  <description>Returns the submission to the private state.</description>
  <action url="%(content_url)s/content_status_modify?workflow_action=retract" category="workflow" icon="">Retract</action>
  <guard>
   <guard-permission>Modify portal content</guard-permission>
   <guard-role>Owner</guard-role>
  </guard>
 </transition>
 <transition transition_id="send_back" title="Send Back" new_state="private" trigger="USER" before_script="" after_script="">
  <description>Return a submission to the private state</description>
  <action url="%(content_url)s/content_status_modify?workflow_action=send_back" category="workflow" icon="">Send Back</action>
  <guard>
   <guard-group>Administrators</guard-group>
  </guard>
 </transition>
 <transition transition_id="submit" title="Submit" new_state="submitted" trigger="USER" before_script="" after_script="">
  <description>Submits item for review.</description>
  <action url="%(content_url)s/content_status_modify?workflow_action=submit" category="workflow" icon="">Submit</action>
  <guard>
   <guard-permission>Change portal events</guard-permission>
   <guard-role>Submitter</guard-role>
  </guard>
 </transition>
 <transition transition_id="to_advisor_review" title="To advisor for review" new_state="advisor_review" trigger="USER" before_script="" after_script="">
  <action url="%(content_url)s/content_status_modify?workflow_action=to_advisor_review" category="workflow" icon="">Send to Advisor for approval and submission</action>
  <guard>
  </guard>
 </transition>
 <transition transition_id="to_alternate" title="To Alternate Visible" new_state="alternate" trigger="AUTOMATIC" before_script="" after_script="">
  <description>Moves to the Alternate Visible State.</description>
  <action url="%(content_url)s/content_status_modify?workflow_action=to_alternate" category="workflow" icon="">Mark as alternate</action>
  <guard>
   <guard-role>Manager</guard-role>
  </guard>
 </transition>
 <transition transition_id="to_alternate_invisible" title="To alternate invisible" new_state="alternate_invisible" trigger="USER" before_script="" after_script="">
  <description>Moves the proposal to the alternate invisible state.</description>
  <action url="%(content_url)s/content_status_modify?workflow_action=to_alternate_invisible" category="workflow" icon="">Mark as Alternate</action>
  <guard>
   <guard-group>Administrators</guard-group>
  </guard>
 </transition>
 <transition transition_id="to_approved" title="Mark as Approved" new_state="approved" trigger="USER" before_script="" after_script="">
  <description>Marks the proposal as approved.</description>
  <action url="%(content_url)s/content_status_modify?workflow_action=to_approved" category="workflow" icon="">Mark as approved</action>
  <guard>
   <guard-group>Administrators</guard-group>
  </guard>
 </transition>
 <transition transition_id="to_approved_invisible" title="To approved invisible" new_state="approved_invisible" trigger="USER" before_script="" after_script="">
  <description>Moves the proposal to the approved invisible state.</description>
  <action url="%(content_url)s/content_status_modify?workflow_action=to_approved_invisible" category="workflow" icon="">Mark as Approved</action>
  <guard>
   <guard-group>Administrators</guard-group>
  </guard>
 </transition>
 <transition transition_id="to_denied" title="Mark as denied" new_state="denied" trigger="USER" before_script="" after_script="">
  <action url="%(content_url)s/content_status_modify?workflow_action=to_denied" category="workflow" icon="">Mark as Denied</action>
  <guard>
   <guard-group>Administrators</guard-group>
  </guard>
 </transition>
 <transition transition_id="to_denied_invisible" title="To denied invisible" new_state="denied_invisible" trigger="USER" before_script="" after_script="">
  <description>This moves the proposal to the Denied Invisible state </description>
  <action url="%(content_url)s/content_status_modify?workflow_action=to_denied_invisible" category="workflow" icon="">Mark as Denied</action>
  <guard>
   <guard-group>Administrators</guard-group>
  </guard>
 </transition>
 <transition transition_id="to_panel_review" title="To Panel Review" new_state="panel_review" trigger="USER" before_script="" after_script="">
  <description>Moves the proposal into the Panel Review State</description>
  <action url="%(content_url)s/content_status_modify?workflow_action=to_panel_review" category="workflow" icon="">Mark as under Panel Review</action>
  <guard>
   <guard-group>Administrators</guard-group>
  </guard>
 </transition>
 <transition transition_id="to_under_review" title="Mark as Under Review" new_state="under_review" trigger="USER" before_script="" after_script="">
  <description>Moves the under review state where it can be reviewed but not modified by the owner.</description>
  <action url="%(content_url)s/content_status_modify?workflow_action=to_under_review" category="workflow" icon="">Mark as under review</action>
  <guard>
   <guard-group>Administrators</guard-group>
  </guard>
 </transition>
 <worklist worklist_id="reviewer_queue" title="">
  <description>Reviewer tasks</description>
  <action url="%(portal_url)s/search?review_state=pending" category="global" icon="">Pending (%(count)d)</action>
  <guard>
   <guard-permission>Review portal content</guard-permission>
  </guard>
  <match name="review_state" values="pending"/>
 </worklist>
 <variable variable_id="action" for_catalog="False" for_status="True" update_always="True">
  <description>Previous transition</description>
  <default>
   
   <expression>transition/getId|nothing</expression>
  </default>
  <guard>
  </guard>
 </variable>
 <variable variable_id="actor" for_catalog="False" for_status="True" update_always="True">
  <description>The ID of the user who performed the last transition</description>
  <default>
   
   <expression>user/getId</expression>
  </default>
  <guard>
  </guard>
 </variable>
 <variable variable_id="comments" for_catalog="False" for_status="True" update_always="True">
  <description>Comment about the last transition</description>
  <default>
   
   <expression>python:state_change.kwargs.get('comment', '')</expression>
  </default>
  <guard>
  </guard>
 </variable>
 <variable variable_id="review_history" for_catalog="False" for_status="False" update_always="False">
  <description>Provides access to workflow history</description>
  <default>
   
   <expression>state_change/getHistory</expression>
  </default>
  <guard>
   <guard-permission>Request review</guard-permission>
   <guard-permission>Review portal content</guard-permission>
  </guard>
 </variable>
 <variable variable_id="time" for_catalog="False" for_status="True" update_always="True">
  <description>When the previous transition was performed</description>
  <default>
   
   <expression>state_change/getDateTime</expression>
  </default>
  <guard>
  </guard>
 </variable>
</dc-workflow>
